{
  "Simple Search: \ud83d\udd25 Alice": {
    "custom_filter": "Alice",
    "custom_sort_key": "",
    "sort_column": 0,
    "ascending": true,
    "default": true
  },
  "Structured Filter: Age >= 50": {
    "custom_filter": "age >= 50",
    "custom_sort_key": "",
    "sort_column": 0,
    "ascending": true,
    "default": false
  },
  "Custom Expression: Tag = 'verified'": {
    "custom_filter": "'verified' in tags",
    "custom_sort_key": "",
    "sort_column": 0,
    "ascending": true,
    "default": false
  },
  "Custom Sort: Len(Name) Descending": {
    "custom_filter": "",
    "custom_sort_key": "len(name)",
    "sort_column": 0,
    "ascending": false,
    "default": false
  },
  "Sort by Email Domain (reverse)": {
    "custom_filter": "",
    "custom_sort_key": "email.split('@')[-1]",
    "sort_column": 0,
    "ascending": false,
    "default": false
  },
  "Filter + Sort: Archived Users Sorted by Age": {
    "custom_filter": "'archived' in tags",
    "custom_sort_key": "age",
    "sort_column": 0,
    "ascending": true,
    "default": false
  },
  "Filter Combo: Admin & Moderator": {
    "custom_filter": "'admin' in tags and 'moderator' in tags",
    "custom_sort_key": "",
    "sort_column": 0,
    "ascending": true,
    "default": false
  },
  "Full Combo: Age < 40 Sorted by Len(Email)": {
    "custom_filter": "age < 40",
    "custom_sort_key": "len(email)",
    "sort_column": 0,
    "ascending": true,
    "default": false
  },
  "Default View: All Active Users": {
    "custom_filter": "id > 0",
    "custom_sort_key": "age",
    "sort_column": 0,
    "ascending": true,
    "default": false
  }
}
